aioiregul/__init__.py
aioiregul/__init__.pyi
aioiregul/cli.py
aioiregul/cli.pyi
aioiregul/iregulapi.py
aioiregul/iregulapi.pyi
aioiregul/models.py
aioiregul/models.pyi
aioiregul/py.typed
aioiregul/v1/__init__.py
aioiregul/v1/__init__.pyi
aioiregul/v2/__init__.py
aioiregul/v2/__init__.pyi
aioiregul/v2/client.py
aioiregul/v2/client.pyi
aioiregul/v2/decoder.py
aioiregul/v2/decoder.pyi
aioiregul/v2/mappers.py
aioiregul/v2/mappers.pyi
aioiregul-0.2.5.dist-info/licenses/LICENSE
aioiregul-0.2.5.dist-info/METADATA
aioiregul-0.2.5.dist-info/WHEEL
aioiregul-0.2.5.dist-info/top_level.txt
aioiregul-0.2.5.dist-info/RECORD
