Metadata-Version: 2.4
Name: aioiregul
Version: 0.2.5
Summary: Asynchronous library to interact with Iregul systems via undocumented API
Author-email: PoppyPop <skytep@gmail.com>
License-Expression: GPL-3.0-or-later
Project-URL: Homepage, https://github.com/PoppyPop/aioiregul
Project-URL: Repository, https://github.com/PoppyPop/aioiregul
Project-URL: Issues, https://github.com/PoppyPop/aioiregul/issues
Project-URL: Bug Tracker, https://github.com/PoppyPop/aioiregul/issues
Keywords: iregul,async,api,home-automation
Classifier: Development Status :: 3 - Alpha
Classifier: Intended Audience :: Developers
Classifier: Programming Language :: Python :: 3
Classifier: Programming Language :: Python :: 3.10
Classifier: Programming Language :: Python :: 3.11
Classifier: Programming Language :: Python :: 3.12
Classifier: Programming Language :: Python :: 3.13
Classifier: Framework :: AsyncIO
Classifier: Topic :: Home Automation
Requires-Python: >=3.10
License-File: LICENSE
Requires-Dist: aiohttp>=3.9.0
Requires-Dist: beautifulsoup4>=4.12.0
Requires-Dist: python-dotenv>=1.0.0
Requires-Dist: python-slugify>=8.0.0
Dynamic: license-file
